<?xml version="1.0"?>
<openerp>
<data>
   <record model="ir.ui.view" id="stock_inventory_line_tree">
        <field name="name">stock.inventory.line.tree</field>
        <field name="model">stock.inventory.line</field>
        <field eval="50" name="priority"/>
        <field name="mode">primary</field>
        <field name="arch" type="xml">
        <tree string="Stock inventory line">
            <field name="product_id"/>
            <field name="categ_id"/>
            <field name="product_type"/>
            <field name="theoretical_std_price"/>
            <field name="standard_price"/>
            <field name="location_id"/>
            <field name="prod_lot_id"/>
            <field name="partner_id"/>
            <field name="theoretical_qty"/>
            <field name="product_qty"/>
            <field name="standard_price"/>
            <field name="value"/>
            <field name="under_repair"/>
            <field name="net_qty"/>
            <field name="net_qty"/>
            <field name="net_value"/>
         </tree>
         </field>
     </record>
</data>
</openerp>